{"chunk_definitions":[{"chunk_id":"cowzqny7uaqlz","chunk_label":"unnamed-chunk-1","document_id":"4825E5F","expansion_state":0,"options":{"engine":"r","include":false,"label":"unnamed-chunk-1"},"row":4,"row_count":1,"visible":true},{"chunk_id":"ckgza6u6lpb67","chunk_label":"unnamed-chunk-2","document_id":"4825E5F","expansion_state":0,"options":{"echo":false,"engine":"r","label":"glvfunctions"},"row":128,"row_count":1,"visible":true},{"chunk_id":"cqnv18x1ehtas","chunk_label":"unnamed-chunk-3","document_id":"4825E5F","expansion_state":0,"options":{"echo":false,"engine":"r","label":"glvex1"},"row":166,"row_count":1,"visible":true},{"chunk_id":"cwexbljnis6yc","chunk_label":"unnamed-chunk-4","document_id":"4825E5F","expansion_state":0,"options":{"engine":"r","label":"glvex2"},"row":206,"row_count":1,"visible":true},{"chunk_id":"cgn0yueydnud5","chunk_label":"unnamed-chunk-5","document_id":"4825E5F","expansion_state":0,"options":{"engine":"r","label":"glvex3"},"row":220,"row_count":1,"visible":true},{"chunk_id":"cj2q344hfvlwl","chunk_label":"unnamed-chunk-6","document_id":"4825E5F","expansion_state":0,"options":{"echo":false,"engine":"r","label":"glvex4"},"row":235,"row_count":1,"visible":true}],"chunk_rendered_width":700,"doc_write_time":1589496002}